tdq/__init__.py
tdq/_version.py
tdq/shell.py
tdq/utils.py
tdq-0.1.8.dist-info/LICENSE
tdq-0.1.8.dist-info/METADATA
tdq-0.1.8.dist-info/WHEEL
tdq-0.1.8.dist-info/entry_points.txt
tdq-0.1.8.dist-info/top_level.txt
tdq-0.1.8.dist-info/RECORD
