Metadata-Version: 2.1
Name: tdq
Version: 0.1.8
Summary: A Treasure Data query shell
Home-page: https://github.com/bachng2017/tdq
Author: bachng
Author-email: bachng@gmail.com
License: Apache
Keywords: python treasuredata shell sql
Platform: UNKNOWN
Classifier: License :: OSI Approved :: Apache Software License
Classifier: Programming Language :: Python :: 3.8
Requires-Python: >=3.8
License-File: LICENSE
Requires-Dist: setuptools (>=40.3.0)
Requires-Dist: td-client
Requires-Dist: prompt-toolkit
Requires-Dist: sqlparse
